{"title":"Combined feed","url":"https://KPOPCORD.github.io/nate_news/all.xml","elements":[{"title":"\"lovely kim jisoo♥\" 블랙핑크 지수, 2022년 음력 새해 인사 (네이트 연예 ─ 아이돌24h ─ 스타 ─ 블랙핑크)","contents":"톱스타뉴스\t\t\t\t\t\t\t<em>02-01 22:15</em>","link":"https://news.nate.com/view/20220201n12345?mid=e0608&isq=9895","retrieved":1643724166213,"image":"https://thumbnews.nateimg.co.kr/news90///news.nateimg.co.kr/orgImg/ts/2022/02/01/14668121_756227_1447_org.jpg"},{"title":"블랙핑크 '뚜두뚜두' 뮤비 18억뷰 돌파…. K팝 그룹 '최초-최고' 신기록 (네이트 연예 ─ 아이돌24h ─ 스타 ─ 블랙핑크)","contents":"스타데일리뉴스\t\t\t\t\t\t\t<em>02-01 17:51</em>","link":"https://news.nate.com/view/20220201n10044?mid=e0608&isq=9895","retrieved":1643706168659,"image":"https://thumbnews.nateimg.co.kr/news90///news.nateimg.co.kr/orgImg/sz/2022/02/01/315480_362201_5019.jpg"},{"title":"블랙핑크 '뚜두뚜두' MV 18억뷰 돌파, K팝 그룹 MV 최초-최고 조회수 (네이트 연예 ─ 아이돌24h ─ 스타 ─ 블랙핑크)","contents":"뉴스엔\t\t\t\t\t\t\t<em>02-01 17:20</em>","link":"https://news.nate.com/view/20220201n09705?mid=e0608&isq=9895","retrieved":1643706168660,"image":"https://thumbnews.nateimg.co.kr/news90///news.nateimg.co.kr/orgImg/nn/2022/02/01/202202011716488010_1.jpg"},{"title":"블랙핑크 지수, '설강화' 촬영 비하인드 사진 공개 (네이트 연예 ─ 아이돌24h ─ 스타 ─ 블랙핑크)","contents":"톱스타뉴스\t\t\t\t\t\t\t<em>01-30 22:25</em>","link":"https://news.nate.com/view/20220130n12419?mid=e0608&isq=9895","retrieved":1643551344522,"image":"https://thumbnews.nateimg.co.kr/news90///news.nateimg.co.kr/orgImg/ts/2022/01/30/14667747_755630_2247_org.jpg"},{"title":"김나영, 블랙핑크 제니와 같은 옷 같은 느낌…♥마이큐도 '좋아요' (네이트 연예 ─ 아이돌24h ─ 스타 ─ 블랙핑크)","contents":"뉴스엔\t\t\t\t\t\t\t<em>01-28 14:02</em>","link":"https://news.nate.com/view/20220128n20398?mid=e0608&isq=9895","retrieved":1643349772001,"image":"https://thumbnews.nateimg.co.kr/news90///news.nateimg.co.kr/orgImg/nn/2022/01/28/202201281340116110_1.jpg"},{"title":"\"압도적 포스\" 블랙핑크 제니, '일론 머스크 전 여친' 그라임스 뮤비 '깜짝' 출연 (네이트 연예 ─ 아이돌24h ─ 스타 ─ 블랙핑크)","contents":"톱스타뉴스\t\t\t\t\t\t\t<em>01-27 16:48</em>","link":"https://news.nate.com/view/20220127n33303?mid=e0608&isq=9895","retrieved":1643274201886,"image":"https://thumbnews.nateimg.co.kr/news90///news.nateimg.co.kr/orgImg/ts/2022/01/27/14667146_754521_4555_org.jpeg"},{"title":"\"JISOO SOLO THIS YEAR\" 블랙핑크 지수, 2022년 솔로 데뷔 앨범 나오나…최근 팬사인회에서 '긍정적인 답변' (네이트 연예 ─ 아이돌24h ─ 스타 ─ 블랙핑크)","contents":"톱스타뉴스\t\t\t\t\t\t\t<em>01-27 11:13</em>","link":"https://news.nate.com/view/20220127n14656?mid=e0608&isq=9895","retrieved":1643252595369,"image":"https://thumbnews.nateimg.co.kr/news90///news.nateimg.co.kr/orgImg/ts/2022/01/27/14667087_754372_759_org.jpg"},{"title":"블랙핑크 지수→김태리, 잇미샤 브랜드 뮤즈 교체 (네이트 연예 ─ 아이돌24h ─ 스타 ─ 블랙핑크)","contents":"뉴스엔\t\t\t\t\t\t\t<em>01-27 08:31</em>","link":"https://news.nate.com/view/20220127n05039?mid=e0608&isq=9895","retrieved":1643242656802,"image":"https://thumbnews.nateimg.co.kr/news90///news.nateimg.co.kr/orgImg/nn/2022/01/27/202201270830400410_1.jpg"},{"title":"블랙핑크, 'Kill This Love' 뮤직비디오 15억뷰 돌파 (네이트 연예 ─ 아이돌24h ─ 스타 ─ 블랙핑크)","contents":"스타데일리뉴스\t\t\t\t\t\t\t<em>01-26 10:01</em>","link":"https://news.nate.com/view/20220126n09867?mid=e0608&isq=9895","retrieved":1643162194657,"image":"https://thumbnews.nateimg.co.kr/news90///news.nateimg.co.kr/orgImg/sz/2022/01/26/315209_361910_033.jpg"},{"title":"블랙핑크 'Kill This Love' 뮤비 15억뷰 돌파…2년9개월만 (네이트 연예 ─ 아이돌24h ─ 스타 ─ 블랙핑크)","contents":"뉴스엔\t\t\t\t\t\t\t<em>01-26 08:04</em>","link":"https://news.nate.com/view/20220126n04518?mid=e0608&isq=9895","retrieved":1643156349764,"image":"https://thumbnews.nateimg.co.kr/news90///news.nateimg.co.kr/orgImg/nn/2022/01/26/202201260802592410_1.jpg"},{"title":"\"기분 좋은 젠득이\" 블랙핑크(BLACKPINK) 제니, 새 브이로그 공개 (네이트 연예 ─ 아이돌24h ─ 스타 ─ 블랙핑크)","contents":"톱스타뉴스\t\t\t\t\t\t\t<em>01-25 19:32</em>","link":"https://news.nate.com/view/20220125n35637?mid=e0608&isq=9895","retrieved":1643108554724,"image":"https://thumbnews.nateimg.co.kr/news90///news.nateimg.co.kr/orgImg/ts/2022/01/25/14666621_753608_3030_org.jpg"},{"title":"\"러블리의 정석\"…블랙핑크 제니, 인형같은 근황 공개 (네이트 연예 ─ 아이돌24h ─ 스타 ─ 블랙핑크)","contents":"톱스타뉴스\t\t\t\t\t\t\t<em>01-25 15:50</em>","link":"https://news.nate.com/view/20220125n26687?mid=e0608&isq=9895","retrieved":1643097798855,"image":"https://thumbnews.nateimg.co.kr/news90///news.nateimg.co.kr/orgImg/ts/2022/01/25/14666567_753495_4736_org.jpg"},{"title":"트와이스 모모, 스타일리시한 블랙&핑크[포토엔HD] (네이트 연예 ─ 아이돌24h ─ 스타 ─ 블랙핑크)","contents":"뉴스엔\t\t\t\t\t\t\t<em>01-23 14:32</em>","link":"https://news.nate.com/view/20220123n08861?mid=e0608&isq=9895","retrieved":1642917885454,"image":"https://thumbnews.nateimg.co.kr/news90///news.nateimg.co.kr/orgImg/nn/2022/01/23/202201231431221810_1.jpg"},{"title":"임영웅, 2022년 1월 가수 브랜드평판 1위…블랙핑크 2위 (네이트 연예 ─ 아이돌24h ─ 스타 ─ 블랙핑크)","contents":"뉴스엔\t\t\t\t\t\t\t<em>01-22 08:31</em>","link":"https://news.nate.com/view/20220122n03042?mid=e0608&isq=9895","retrieved":1642810701910,"image":"https://thumbnews.nateimg.co.kr/news90///news.nateimg.co.kr/orgImg/nn/2022/01/22/202201220828268010_51.jpg"},{"title":"\"언니는 역시 대단한 사람\"…블랙핑크 지수, 故 김미수 향한 그리움 (네이트 연예 ─ 아이돌24h ─ 스타 ─ 블랙핑크)","contents":"톱스타뉴스\t\t\t\t\t\t\t<em>01-21 16:22</em>","link":"https://news.nate.com/view/20220121n23854?mid=e0608&isq=9895","retrieved":1642755739324,"image":"https://thumbnews.nateimg.co.kr/news90///news.nateimg.co.kr/orgImg/ts/2022/01/21/14665771_752116_2038_org.jpg"},{"title":"[스타서베이] 3월생 스타 생일 축하 기부 서포트 홍지윤 현재 1위…황윤성·남승민·레드벨벳 아이린·윤지성 추격 중 (네이트 연예 ─ 아이돌24h ─ 스타 ─ 레드벨벳)","contents":"톱스타뉴스\t\t\t\t\t\t\t<em>02-04 21:32</em>","link":"https://news.nate.com/view/20220204n30722?mid=e0608&isq=9012","retrieved":1643979844142,"image":"https://thumbnews.nateimg.co.kr/news90///news.nateimg.co.kr/orgImg/ts/2022/02/04/14668788_757358_3012_org.jpg"},{"title":"레드벨벳 웬디 '웬디의 영스는 사랑'[포토엔HD] (네이트 연예 ─ 아이돌24h ─ 스타 ─ 레드벨벳)","contents":"뉴스엔\t\t\t\t\t\t\t<em>02-04 17:32</em>","link":"https://news.nate.com/view/20220204n26210?mid=e0608&isq=9012","retrieved":1643965419516,"image":"https://thumbnews.nateimg.co.kr/news90///news.nateimg.co.kr/orgImg/nn/2022/02/04/202202041730533510_1.jpg"},{"title":"레드벨벳 웬디 '파워FM 웬디의 영스트리트~'[포토엔HD] (네이트 연예 ─ 아이돌24h ─ 스타 ─ 레드벨벳)","contents":"뉴스엔\t\t\t\t\t\t\t<em>02-04 17:29</em>","link":"https://news.nate.com/view/20220204n26090?mid=e0608&isq=9012","retrieved":1643965419516,"image":"https://thumbnews.nateimg.co.kr/news90///news.nateimg.co.kr/orgImg/nn/2022/02/04/202202041728143510_1.jpg"},{"title":"레드벨벳 웬디 '오늘도 파이팅!'[포토엔HD] (네이트 연예 ─ 아이돌24h ─ 스타 ─ 레드벨벳)","contents":"뉴스엔\t\t\t\t\t\t\t<em>02-04 17:27</em>","link":"https://news.nate.com/view/20220204n26008?mid=e0608&isq=9012","retrieved":1643965419516,"image":"https://thumbnews.nateimg.co.kr/news90///news.nateimg.co.kr/orgImg/nn/2022/02/04/202202041726163510_1.jpg"},{"title":"레드벨벳 웬디 '조신하게 큰절 올리겠습니다~'[포토엔HD] (네이트 연예 ─ 아이돌24h ─ 스타 ─ 레드벨벳)","contents":"뉴스엔\t\t\t\t\t\t\t<em>02-04 17:25</em>","link":"https://news.nate.com/view/20220204n25914?mid=e0608&isq=9012","retrieved":1643965419520,"image":"https://thumbnews.nateimg.co.kr/news90///news.nateimg.co.kr/orgImg/nn/2022/02/04/202202041724053510_1.jpg"},{"title":"레드벨벳 웬디, 22년에도 '완소'하고픈 '완디' 많관부~ (영스트리트 출근)[뉴스엔TV] (네이트 연예 ─ 아이돌24h ─ 스타 ─ 레드벨벳)","contents":"뉴스엔\t\t\t\t\t\t\t<em>02-04 17:22</em>","link":"https://news.nate.com/view/20220204n25814?mid=e0608&isq=9012","retrieved":1643965419542,"image":"https://thumbnews.nateimg.co.kr/news90///news.nateimg.co.kr/orgImg/nn/2022/02/04/202202041720481310_1.jpg"},{"title":"레드벨벳 웬디 '올해만 벌써 세번째 세배'[포토엔HD] (네이트 연예 ─ 아이돌24h ─ 스타 ─ 레드벨벳)","contents":"뉴스엔\t\t\t\t\t\t\t<em>02-04 17:20</em>","link":"https://news.nate.com/view/20220204n25755?mid=e0608&isq=9012","retrieved":1643965419542,"image":"https://thumbnews.nateimg.co.kr/news90///news.nateimg.co.kr/orgImg/nn/2022/02/04/202202041719433510_1.jpg"},{"title":"레드벨벳 웬디 '하트까지 예쁜 완디'[포토엔HD] (네이트 연예 ─ 아이돌24h ─ 스타 ─ 레드벨벳)","contents":"뉴스엔\t\t\t\t\t\t\t<em>02-04 17:15</em>","link":"https://news.nate.com/view/20220204n25606?mid=e0608&isq=9012","retrieved":1643965419542,"image":"https://thumbnews.nateimg.co.kr/news90///news.nateimg.co.kr/orgImg/nn/2022/02/04/202202041714023510_1.jpg"},{"title":"레드벨벳 웬디 '완디가 사랑합니다~'[포토엔HD] (네이트 연예 ─ 아이돌24h ─ 스타 ─ 레드벨벳)","contents":"뉴스엔\t\t\t\t\t\t\t<em>02-04 17:12</em>","link":"https://news.nate.com/view/20220204n25510?mid=e0608&isq=9012","retrieved":1643965419546,"image":"https://thumbnews.nateimg.co.kr/news90///news.nateimg.co.kr/orgImg/nn/2022/02/04/202202041710483510_1.jpg"},{"title":"레드벨벳 웬디 '애교를 부르는 하트'[포토엔HD] (네이트 연예 ─ 아이돌24h ─ 스타 ─ 레드벨벳)","contents":"뉴스엔\t\t\t\t\t\t\t<em>02-04 17:10</em>","link":"https://news.nate.com/view/20220204n25455?mid=e0608&isq=9012","retrieved":1643965419546,"image":"https://thumbnews.nateimg.co.kr/news90///news.nateimg.co.kr/orgImg/nn/2022/02/04/202202041709373510_1.jpg"},{"title":"레드벨벳 웬디 '시력 레베럽 시켜주는 아름다움'[포토엔HD] (네이트 연예 ─ 아이돌24h ─ 스타 ─ 레드벨벳)","contents":"뉴스엔\t\t\t\t\t\t\t<em>02-04 17:07</em>","link":"https://news.nate.com/view/20220204n25383?mid=e0608&isq=9012","retrieved":1643965419547,"image":"https://thumbnews.nateimg.co.kr/news90///news.nateimg.co.kr/orgImg/nn/2022/02/04/202202041705503510_1.jpg"},{"title":"레드벨벳 웬디 '영스의 완디는 사랑입니다'[포토엔HD] (네이트 연예 ─ 아이돌24h ─ 스타 ─ 레드벨벳)","contents":"뉴스엔\t\t\t\t\t\t\t<em>02-04 17:03</em>","link":"https://news.nate.com/view/20220204n25281?mid=e0608&isq=9012","retrieved":1643965419547,"image":"https://thumbnews.nateimg.co.kr/news90///news.nateimg.co.kr/orgImg/nn/2022/02/04/202202041701523510_1.jpg"},{"title":"레드벨벳 웬디 '볼하트 주머니에 꽉 찬 福'[포토엔HD] (네이트 연예 ─ 아이돌24h ─ 스타 ─ 레드벨벳)","contents":"뉴스엔\t\t\t\t\t\t\t<em>02-04 16:58</em>","link":"https://news.nate.com/view/20220204n25097?mid=e0608&isq=9012","retrieved":1643965419547,"image":"https://thumbnews.nateimg.co.kr/news90///news.nateimg.co.kr/orgImg/nn/2022/02/04/202202041657343510_1.jpg"},{"title":"레드벨벳 웬디 '머리부터 발끝까지 다 사랑스러워~'[포토엔HD] (네이트 연예 ─ 아이돌24h ─ 스타 ─ 레드벨벳)","contents":"뉴스엔\t\t\t\t\t\t\t<em>02-04 16:56</em>","link":"https://news.nate.com/view/20220204n25016?mid=e0608&isq=9012","retrieved":1643965419547,"image":"https://thumbnews.nateimg.co.kr/news90///news.nateimg.co.kr/orgImg/nn/2022/02/04/202202041655183510_1.jpg"},{"title":"레드벨벳 웬디 '활짝 만개한 꽃'[포토엔HD] (네이트 연예 ─ 아이돌24h ─ 스타 ─ 레드벨벳)","contents":"뉴스엔\t\t\t\t\t\t\t<em>02-04 16:52</em>","link":"https://news.nate.com/view/20220204n24845?mid=e0608&isq=9012","retrieved":1643965419547,"image":"https://thumbnews.nateimg.co.kr/news90///news.nateimg.co.kr/orgImg/nn/2022/02/04/202202041651353510_1.jpg"},{"title":"방탄소년단 진, 머리가 작은 거야? 새우가 큰 거야? (네이트 연예 ─ 아이돌24h ─ 스타 ─ BTS)","contents":"스포츠조선\t\t\t\t\t\t\t<em>02-05 06:51</em>","link":"https://news.nate.com/view/20220205n01773?mid=e0608&isq=9009","retrieved":1644012286151,"image":"https://thumbnews.nateimg.co.kr/news90///news.nateimg.co.kr/orgImg/sc/2022/02/05/2022020601000243800016391.jpg"},{"title":"방탄소년단 진, 킹사이즈 새우 들고 \"여보세요\"…장꾸 매력 (네이트 연예 ─ 아이돌24h ─ 스타 ─ BTS)","contents":"마이데일리\t\t\t\t\t\t\t<em>02-05 06:02</em>","link":"https://news.nate.com/view/20220205n01269?mid=e0608&isq=9009","retrieved":1644012286153,"image":"https://thumbnews.nateimg.co.kr/news90///news.nateimg.co.kr/orgImg/my/2022/02/05/202202042226698118_1.jpg"},{"title":"방탄소년단 지민 '필터' 유튜브 누적 8600만뷰 달성 (네이트 연예 ─ 아이돌24h ─ 스타 ─ BTS)","contents":"스타뉴스\t\t\t\t\t\t\t<em>02-05 03:20</em>","link":"https://news.nate.com/view/20220205n00754?mid=e0608&isq=9009","retrieved":1644001497236,"image":"https://thumbnews.nateimg.co.kr/news90///news.nateimg.co.kr/orgImg/tn/2022/02/05/2022020501451418782_1.jpg"},{"title":"방탄소년단 진 \"여보세요\" [스타IN★] (네이트 연예 ─ 아이돌24h ─ 스타 ─ BTS)","contents":"스타뉴스\t\t\t\t\t\t\t<em>02-05 01:21</em>","link":"https://news.nate.com/view/20220205n00418?mid=e0608&isq=9009","retrieved":1643994327330,"image":"https://thumbnews.nateimg.co.kr/news90///news.nateimg.co.kr/orgImg/tn/2022/02/05/2022020501111914195_1.jpg"},{"title":"'스케치북' 이찬원, BTS 정국X송가인 제치고 '기대주' 1위…\"과찬이다\"[별별TV] (네이트 연예 ─ 아이돌24h ─ 스타 ─ BTS)","contents":"스타뉴스\t\t\t\t\t\t\t<em>02-05 01:09</em>","link":"https://news.nate.com/view/20220205n00232?mid=e0608&isq=9009","retrieved":1643990709656,"image":"https://thumbnews.nateimg.co.kr/news90///news.nateimg.co.kr/orgImg/tn/2022/02/05/tn_1643990943693_544336_0.jpg"},{"title":"\"BTS도 좋은 일 하는데\"…이영자, 돈쭐 협상 (편스토랑)[종합] (네이트 연예 ─ 아이돌24h ─ 스타 ─ BTS)","contents":"엑스포츠뉴스\t\t\t\t\t\t\t<em>02-05 00:51</em>","link":"https://news.nate.com/view/20220205n00309?mid=e0608&isq=9009","retrieved":1643990709655,"image":"https://thumbnews.nateimg.co.kr/news90///news.nateimg.co.kr/orgImg/xs/2022/02/05/1643978523514369.jpg"},{"title":"'마이웨이' 허참 \"BTS 빌보드 차트 1위, 꿈도 못 꿨던 일\" [별별TV] (네이트 연예 ─ 아이돌24h ─ 스타 ─ BTS)","contents":"스타뉴스\t\t\t\t\t\t\t<em>02-04 23:34</em>","link":"https://news.nate.com/view/20220204n32798?mid=e0608&isq=9009","retrieved":1643987078053,"image":"https://thumbnews.nateimg.co.kr/news90///news.nateimg.co.kr/orgImg/tn/2022/02/04/2022020418485639217_1.jpg"},{"title":"팬심 흔드는 외모…BTS 지민 '만찢 비주얼 스타' 1위 질주 (네이트 연예 ─ 아이돌24h ─ 스타 ─ BTS)","contents":"스타뉴스\t\t\t\t\t\t\t<em>02-04 22:40</em>","link":"https://news.nate.com/view/20220204n31958?mid=e0608&isq=9009","retrieved":1643983487680,"image":"https://thumbnews.nateimg.co.kr/news90///news.nateimg.co.kr/orgImg/tn/2022/02/04/2022020422250764929_1.jpg"},{"title":"방탄소년단 진, 新따귀머리+꾸깃 흰티…일상 속 장꾸美 [리포트:컷] (네이트 연예 ─ 아이돌24h ─ 스타 ─ BTS)","contents":"TV리포트\t\t\t\t\t\t\t<em>02-04 21:42</em>","link":"https://news.nate.com/view/20220204n30909?mid=e0608&isq=9009","retrieved":1643979920956,"image":"https://thumbnews.nateimg.co.kr/news90///news.nateimg.co.kr/orgImg/tr/2022/02/04/d4b23e08-8265-4c9f-b539-e85e5697e9aa.jpg"},{"title":"\"내일이구만\" 방탄소년단 슈가, 정국XSUGA 노래 발매 예고 [★SHOT!] (네이트 연예 ─ 아이돌24h ─ 스타 ─ BTS)","contents":"OSEN\t\t\t\t\t\t\t<em>02-04 19:43</em>","link":"https://news.nate.com/view/20220204n28955?mid=e0608&isq=9009","retrieved":1643972693258,"image":"https://thumbnews.nateimg.co.kr/news90///news.nateimg.co.kr/orgImg/pt/2022/02/04/202202041925778545_61fd019550a70.png"},{"title":"방탄소년단, 또 日 오리콘 신기록…'Dynamite' 이어 'Butter'도 누적 포인트 200만 달성 (네이트 연예 ─ 아이돌24h ─ 스타 ─ BTS)","contents":"톱스타뉴스\t\t\t\t\t\t\t<em>02-04 13:24</em>","link":"https://news.nate.com/view/20220204n16303?mid=e0608&isq=9009","retrieved":1643951106338,"image":"https://thumbnews.nateimg.co.kr/news90///news.nateimg.co.kr/orgImg/ts/2022/02/04/14668642_757164_237_org.jpg"},{"title":"방탄소년단 정국, '최고의 육각형 남자 아이돌' 1위 (네이트 연예 ─ 아이돌24h ─ 스타 ─ BTS)","contents":"MK스포츠\t\t\t\t\t\t\t<em>02-04 11:23</em>","link":"https://news.nate.com/view/20220204n12846?mid=e0608&isq=9009","retrieved":1643943908282,"image":"https://thumbnews.nateimg.co.kr/news90///news.nateimg.co.kr/orgImg/aa/2022/02/04/20220204_1643941336.jpg"},{"title":"방탄소년단, 日 오리콘 신기록…'버터'로 '누적 200만 포인트' 돌파 (네이트 연예 ─ 아이돌24h ─ 스타 ─ BTS)","contents":"스포츠월드\t\t\t\t\t\t\t<em>02-04 11:10</em>","link":"https://news.nate.com/view/20220204n07396?mid=e0608&isq=9009","retrieved":1643939065077,"image":"https://thumbnews.nateimg.co.kr/news90///news.nateimg.co.kr/orgImg/sw/2022/02/04/20220204504250.jpg"},{"title":"음콘협 \"BTS 팬클럽 아미, 하이브 NFT 사업 반대 의미 있는 행보\" (네이트 연예 ─ 아이돌24h ─ 스타 ─ BTS)","contents":"MK스포츠\t\t\t\t\t\t\t<em>02-04 10:57</em>","link":"https://news.nate.com/view/20220204n11379?mid=e0608&isq=9009","retrieved":1643940700639,"image":"https://thumbnews.nateimg.co.kr/news90///news.nateimg.co.kr/orgImg/aa/2022/02/04/20220204_1643939696.jpg"},{"title":"방탄소년단 정국 'Hate Everything' 커버 공개…버터처럼 녹아든다 (네이트 연예 ─ 아이돌24h ─ 스타 ─ BTS)","contents":"뉴스엔\t\t\t\t\t\t\t<em>02-04 10:51</em>","link":"https://news.nate.com/view/20220204n11077?mid=e0608&isq=9009","retrieved":1643940700652,"image":"https://thumbnews.nateimg.co.kr/news90///news.nateimg.co.kr/orgImg/nn/2022/02/04/202202041002160410_1.jpg"}]}