{"title":"네이트 연예 ─ 아이돌24h ─ 스타 ─ BTS","url":"https://news.nate.com/ent/idolHissue?hissueSq=9009&mid=e0608","favicon":"https://news.nate.com/ent/favicon.ico","elements":[{"title":"BTS 지민, 음악 에너지가 넘치는 파워풀 보컬 소유자","contents":"엑스포츠뉴스\t\t\t\t\t\t\t<em>02-20 09:02</em>","link":"https://news.nate.com/view/20220220n02413?mid=e0608&isq=9009","retrieved":1645316871947,"image":"https://thumbnews.nateimg.co.kr/news90///news.nateimg.co.kr/orgImg/xs/2022/02/20/1645315261739985.jpg"},{"title":"방탄소년단 지민, \"음악에 에너지가 넘치는 '파워풀'한 보컬의 소유자는?\" 익디 투표 1위","contents":"톱스타뉴스\t\t\t\t\t\t\t<em>02-20 08:36</em>","link":"https://news.nate.com/view/20220220n02081?mid=e0608&isq=9009","retrieved":1645316871949,"image":"https://thumbnews.nateimg.co.kr/news90///news.nateimg.co.kr/orgImg/ts/2022/02/20/14672019_762663_3451_org.jpg"},{"title":"\"오구오구 겸둥이♥\" 방탄소년단 지민, 유자향 솔솔 '인간 비타민'","contents":"스타뉴스\t\t\t\t\t\t\t<em>02-20 08:20</em>","link":"https://news.nate.com/view/20220220n01952?mid=e0608&isq=9009","retrieved":1645316871950,"image":"https://thumbnews.nateimg.co.kr/news90///news.nateimg.co.kr/orgImg/tn/2022/02/20/2022022007082737238_1.jpg"},{"title":"백종원, \"BTS 진, 음식에 대한 도전 되게 잘해\"","contents":"엑스포츠뉴스\t\t\t\t\t\t\t<em>02-20 08:09</em>","link":"https://news.nate.com/view/20220220n01888?mid=e0608&isq=9009","retrieved":1645316871952,"image":"https://thumbnews.nateimg.co.kr/news90///news.nateimg.co.kr/orgImg/xs/2022/02/20/1645311970288614.jpg"},{"title":"방탄소년단 지민, '음악 에너지 넘치는 파워풀 보컬 소유자' 1위","contents":"스타뉴스\t\t\t\t\t\t\t<em>02-20 07:59</em>","link":"https://news.nate.com/view/20220220n01765?mid=e0608&isq=9009","retrieved":1645316871952,"image":"https://thumbnews.nateimg.co.kr/news90///news.nateimg.co.kr/orgImg/tn/2022/02/20/2022022006412415978_2.jpg"},{"title":"방탄소년단 슈가 프로듀싱 아이유 '에잇' 스포이파이 1억 8800만 스트리밍 돌파…인기ing","contents":"스타뉴스\t\t\t\t\t\t\t<em>02-20 07:52</em>","link":"https://news.nate.com/view/20220220n01706?mid=e0608&isq=9009","retrieved":1645311888206,"image":"https://thumbnews.nateimg.co.kr/news90///news.nateimg.co.kr/orgImg/tn/2022/02/20/2022022007504831390_1.jpg"},{"title":"방탄소년단 슈가 '오버 더 호라이즌' 유튜브 200만 좋아요♥","contents":"스타뉴스\t\t\t\t\t\t\t<em>02-20 07:50</em>","link":"https://news.nate.com/view/20220220n01692?mid=e0608&isq=9009","retrieved":1645311888207,"image":"https://thumbnews.nateimg.co.kr/news90///news.nateimg.co.kr/orgImg/tn/2022/02/20/2022022007313919491_1.jpg"},{"title":"\"감독님이 너무 꽃미남♥\" 방탄소년단 정국, G.C.F 찍는 꽃감독","contents":"스타뉴스\t\t\t\t\t\t\t<em>02-20 07:44</em>","link":"https://news.nate.com/view/20220220n01639?mid=e0608&isq=9009","retrieved":1645311888208,"image":"https://thumbnews.nateimg.co.kr/news90///news.nateimg.co.kr/orgImg/tn/2022/02/20/2022022007401321366_1.jpg"},{"title":"방탄소년단 정국 'Stay Alive' 韓OST 최초·유일 英오피셜 싱글 차트 데뷔 '新기록'","contents":"스타뉴스\t\t\t\t\t\t\t<em>02-20 07:38</em>","link":"https://news.nate.com/view/20220220n01613?mid=e0608&isq=9009","retrieved":1645311888210,"image":"https://thumbnews.nateimg.co.kr/news90///news.nateimg.co.kr/orgImg/tn/2022/02/20/2022022007335997711_1.jpg"},{"title":"5억에 성큼…방탄소년단 슈가 어거스트디 'D-2' 믹스테이프 스포티파이 4억 9200만","contents":"스타뉴스\t\t\t\t\t\t\t<em>02-20 07:30</em>","link":"https://news.nate.com/view/20220220n01586?mid=e0608&isq=9009","retrieved":1645311888212,"image":"https://thumbnews.nateimg.co.kr/news90///news.nateimg.co.kr/orgImg/tn/2022/02/20/2022022007273847786_1.jpg"},{"title":"방탄소년단 정국 'Stay Alive' 스포티파이 글로벌·韓주간 1위…글로벌 차트 韓솔로곡 최다 1880만 스트리밍 데뷔","contents":"스타뉴스\t\t\t\t\t\t\t<em>02-20 07:27</em>","link":"https://news.nate.com/view/20220220n01581?mid=e0608&isq=9009","retrieved":1645311888214,"image":"https://thumbnews.nateimg.co.kr/news90///news.nateimg.co.kr/orgImg/tn/2022/02/20/2022022007231830932_1.jpg"},{"title":"\"아 얼굴 진짜\" 방탄소년단 뷔, 히어로 vs 빌런…'장르가 김태형'","contents":"스타뉴스\t\t\t\t\t\t\t<em>02-20 07:23</em>","link":"https://news.nate.com/view/20220220n01566?mid=e0608&isq=9009","retrieved":1645311888221,"image":"https://thumbnews.nateimg.co.kr/news90///news.nateimg.co.kr/orgImg/tn/2022/02/20/2022022007183223381_1.jpg"},{"title":"USA~♡ 방탄소년단 진, '미국에서 가장 있는 있는 아이돌' 1위","contents":"스타뉴스\t\t\t\t\t\t\t<em>02-20 07:16</em>","link":"https://news.nate.com/view/20220220n01549?mid=e0608&isq=9009","retrieved":1645311888224,"image":"https://thumbnews.nateimg.co.kr/news90///news.nateimg.co.kr/orgImg/tn/2022/02/20/2022022007083867908_1.jpg"},{"title":"방탄소년단 진 '슈퍼 참치', '놀라운 토요일' 출제…더 놀라운 우승자","contents":"스타뉴스\t\t\t\t\t\t\t<em>02-20 07:05</em>","link":"https://news.nate.com/view/20220220n01472?mid=e0608&isq=9009","retrieved":1645311888224,"image":"https://thumbnews.nateimg.co.kr/news90///news.nateimg.co.kr/orgImg/tn/2022/02/20/2022022006564163116_1.jpg"},{"title":"방탄소년단 뷔 'Christmas Tree' 샤잠 재팬 53일 1위…大기록","contents":"스타뉴스\t\t\t\t\t\t\t<em>02-20 06:45</em>","link":"https://news.nate.com/view/20220220n01292?mid=e0608&isq=9009","retrieved":1645308294497,"image":"https://thumbnews.nateimg.co.kr/news90///news.nateimg.co.kr/orgImg/tn/2022/02/20/2022022006410465855_1.jpg"}]}