{"title":"네이트 연예 ─ 아이돌24h ─ 스타 ─ BTS","url":"https://news.nate.com/ent/idolHissue?hissueSq=9009&mid=e0608","favicon":"https://news.nate.com/ent/favicon.ico","elements":[{"title":"지난해 팔린 음반 3장 중 2장은 SM·하이브…BTS·NCT 효자","contents":"조이뉴스24\t\t\t\t\t\t\t<em>01-11 09:10</em>","link":"https://news.nate.com/view/20220111n05836?mid=e0608&isq=9009","retrieved":1641860524202,"image":"https://thumbnews.nateimg.co.kr/news90///news.nateimg.co.kr/orgImg/jn/2022/01/11/735eee0bccc643.jpg"},{"title":"[독자추천종합순위] 영탁 98회째 1위, 2위 임영웅에 398표 앞서…3위 방탄소년단 지민·4위 이찬원·5위 장민호","contents":"톱스타뉴스\t\t\t\t\t\t\t<em>01-11 09:09</em>","link":"https://news.nate.com/view/20220111n05771?mid=e0608&isq=9009","retrieved":1641860524202,"image":"https://thumbnews.nateimg.co.kr/news90///news.nateimg.co.kr/orgImg/ts/2022/01/11/14663158_747856_751_org.jpg"},{"title":"PJM1 고대…'음악PM성공' 방탄소년단 지민, 솔로 활동 '기대UP'","contents":"스타뉴스\t\t\t\t\t\t\t<em>01-11 08:59</em>","link":"https://news.nate.com/view/20220111n05301?mid=e0608&isq=9009","retrieved":1641860524205,"image":"https://thumbnews.nateimg.co.kr/news90///news.nateimg.co.kr/orgImg/tn/2022/01/11/2022011108503662580_1.jpg"},{"title":"BTS 진, 무결점 비주얼로 여심 저격","contents":"엑스포츠뉴스\t\t\t\t\t\t\t<em>01-11 08:56</em>","link":"https://news.nate.com/view/20220111n05184?mid=e0608&isq=9009","retrieved":1641860524214,"image":"https://thumbnews.nateimg.co.kr/news90///news.nateimg.co.kr/orgImg/xs/2022/01/11/1641858946869983.jpg"},{"title":"[댓글종합순위] 영탁 143회째 1위, 2위 박서진에 718개 앞서…3위 이찬원·4위 방탄소년단 지민·5위 강혜연","contents":"톱스타뉴스\t\t\t\t\t\t\t<em>01-11 08:45</em>","link":"https://news.nate.com/view/20220111n04860?mid=e0608&isq=9009","retrieved":1641860524214,"image":"https://thumbnews.nateimg.co.kr/news90///news.nateimg.co.kr/orgImg/ts/2022/01/11/14663157_747851_4355_org.jpg"},{"title":"\"JIMIN is fab♥\" 방탄소년단 지민 英빅토리아 베컴 편집장 4년째 주목…'패션계 원픽'","contents":"스타뉴스\t\t\t\t\t\t\t<em>01-11 08:14</em>","link":"https://news.nate.com/view/20220111n04036?mid=e0608&isq=9009","retrieved":1641860524214,"image":"https://thumbnews.nateimg.co.kr/news90///news.nateimg.co.kr/orgImg/tn/2022/01/11/2022011108074334623_1.jpg"},{"title":"BTS 정국, B컷도 A컷으로 만드는 비주얼","contents":"엑스포츠뉴스\t\t\t\t\t\t\t<em>01-11 08:00</em>","link":"https://news.nate.com/view/20220111n03684?mid=e0608&isq=9009","retrieved":1641860524215,"image":"https://thumbnews.nateimg.co.kr/news90///news.nateimg.co.kr/orgImg/xs/2022/01/11/1641855520011930.jpg"},{"title":"방탄소년단 제이홉, 새벽 바닷가에서 뭐하나? 누가 찍어준 것인지 궁금증 커져","contents":"스포츠조선\t\t\t\t\t\t\t<em>01-11 07:58</em>","link":"https://news.nate.com/view/20220111n03643?mid=e0608&isq=9009","retrieved":1641860524215,"image":"https://thumbnews.nateimg.co.kr/news90///news.nateimg.co.kr/orgImg/sc/2022/01/11/2022011201000673000041052.jpg"},{"title":"방탄소년단 슈가 어거스트디 'Agust D' MV 1억 4100만뷰 돌파","contents":"스타뉴스\t\t\t\t\t\t\t<em>01-11 07:45</em>","link":"https://news.nate.com/view/20220111n03396?mid=e0608&isq=9009","retrieved":1641855944038,"image":"https://thumbnews.nateimg.co.kr/news90///news.nateimg.co.kr/orgImg/tn/2022/01/11/2022011107421886448_1.jpg"},{"title":"방탄소년단 정국, 인도에서 '가장 인기있는 K팝 男 아이돌' 선정","contents":"스포츠조선\t\t\t\t\t\t\t<em>01-11 07:36</em>","link":"https://news.nate.com/view/20220111n03247?mid=e0608&isq=9009","retrieved":1641855944041,"image":"https://thumbnews.nateimg.co.kr/news90///news.nateimg.co.kr/orgImg/sc/2022/01/11/2022011201000672100040992.jpg"},{"title":"방탄소년단 마스크 논란, \"5천원 너무 비싸\" vs \"굿즈로 손색 없어\"","contents":"일간스포츠\t\t\t\t\t\t\t<em>01-11 07:31</em>","link":"https://news.nate.com/view/20220111n03156?mid=e0608&isq=9009","retrieved":1641855944042,"image":"https://thumbnews.nateimg.co.kr/news90///news.nateimg.co.kr/orgImg/is/2022/01/11/htm_2022011172543164447.JPG"},{"title":"방탄소년단 슈가 'Interlude:Shadow' 발매 2주년 전 세계 팬들 축하…HAPPY SHADOW-VERSARY","contents":"스타뉴스\t\t\t\t\t\t\t<em>01-11 07:23</em>","link":"https://news.nate.com/view/20220111n03065?mid=e0608&isq=9009","retrieved":1641855944044,"image":"https://thumbnews.nateimg.co.kr/news90///news.nateimg.co.kr/orgImg/tn/2022/01/11/2022011107172791580_1.jpg"},{"title":"\"빠져든다아아아아~♥\" 방탄소년단 정국, 1급 청정 미모","contents":"스타뉴스\t\t\t\t\t\t\t<em>01-11 07:16</em>","link":"https://news.nate.com/view/20220111n02992?mid=e0608&isq=9009","retrieved":1641855944046,"image":"https://thumbnews.nateimg.co.kr/news90///news.nateimg.co.kr/orgImg/tn/2022/01/11/2022011107104374742_1.jpg"},{"title":"방탄소년단 정국 '유포리아' 日스포티파이 K팝 솔로곡 최장 차트인 1위+최다 스트리밍 기록","contents":"스타뉴스\t\t\t\t\t\t\t<em>01-11 07:10</em>","link":"https://news.nate.com/view/20220111n02916?mid=e0608&isq=9009","retrieved":1641855944047,"image":"https://thumbnews.nateimg.co.kr/news90///news.nateimg.co.kr/orgImg/tn/2022/01/11/2022011107062889304_1.jpg"},{"title":"방탄소년단 진 'Yours' 샤잠 '글로벌 TOP 200' Film·TV&Stage 63일 연속 1위…'글로벌 음원 파워'","contents":"스타뉴스\t\t\t\t\t\t\t<em>01-11 07:06</em>","link":"https://news.nate.com/view/20220111n02856?mid=e0608&isq=9009","retrieved":1641855944049,"image":"https://thumbnews.nateimg.co.kr/news90///news.nateimg.co.kr/orgImg/tn/2022/01/11/2022011106563372408_1.jpg"}]}