{"title":"네이트 연예 ─ 아이돌24h ─ 스타 ─ BTS","url":"https://news.nate.com/ent/idolHissue?hissueSq=9009&mid=e0608","favicon":"https://news.nate.com/ent/favicon.ico","elements":[{"title":"방탄소년단 뷔 팔로워 4000만 돌파…국내 최초","contents":"스포츠경향\t\t\t\t\t\t\t<em>04-20 09:02</em>","link":"https://news.nate.com/view/20220420n07166?mid=e0608&isq=9009","retrieved":1650414362867,"image":"https://thumbnews.nateimg.co.kr/news90///news.nateimg.co.kr/orgImg/kz/2022/04/20/l_2022042002001126700215581.jpg"},{"title":"방탄소년단(BTS) RM 따라 미술관 가자-이재효 갤러리 편 @rkive [아트 in K팝]","contents":"스포츠서울\t\t\t\t\t\t\t<em>04-20 09:00</em>","link":"https://news.nate.com/view/20220420n07283?mid=e0608&isq=9009","retrieved":1650414362869,"image":"https://thumbnews.nateimg.co.kr/news90///news.nateimg.co.kr/orgImg/sp/2022/04/20/20220419133822_0101.jpg"},{"title":"방탄소년단(BTS) 진, 특별한 귀국 인사 \"잘 도착했습니다\"","contents":"엑스포츠뉴스\t\t\t\t\t\t\t<em>04-20 09:00</em>","link":"https://news.nate.com/view/20220420n07273?mid=e0608&isq=9009","retrieved":1650414362872,"image":"https://thumbnews.nateimg.co.kr/news90///news.nateimg.co.kr/orgImg/xs/2022/04/20/1650412749501445.jpg"},{"title":"\"태태는 사복까지 안구 복지\" 방탄소년단 뷔, 센스 있는 패션 '글로벌 패션 아이콘'","contents":"스타뉴스\t\t\t\t\t\t\t<em>04-20 08:52</em>","link":"https://news.nate.com/view/20220420n06949?mid=e0608&isq=9009","retrieved":1650414362875,"image":"https://thumbnews.nateimg.co.kr/news90///news.nateimg.co.kr/orgImg/tn/2022/04/20/2022042008484469068_1.jpg"},{"title":"방탄소년단 RM, 뒤늦게 입국 완료…6월 컴백 준비 본격화 할까[종합]","contents":"스타뉴스\t\t\t\t\t\t\t<em>04-20 08:29</em>","link":"https://news.nate.com/view/20220420n06152?mid=e0608&isq=9009","retrieved":1650414362876,"image":"https://thumbnews.nateimg.co.kr/news90///news.nateimg.co.kr/orgImg/tn/2022/04/20/2022042008064287561_1.jpg"},{"title":"방탄소년단(BTS) 제이홉, 美 지상파 CBS 드라마 '더 네이버후드' 등장 눈길","contents":"엑스포츠뉴스\t\t\t\t\t\t\t<em>04-20 08:19</em>","link":"https://news.nate.com/view/20220420n05886?mid=e0608&isq=9009","retrieved":1650414362884,"image":"https://thumbnews.nateimg.co.kr/news90///news.nateimg.co.kr/orgImg/xs/2022/04/20/1650410297060778.jpg"},{"title":"신인가수 화연이 누구길래? '방탄소년단 아버지' 방시혁 프로듀싱한 '꽃핀다'로 데뷔","contents":"스포츠조선\t\t\t\t\t\t\t<em>04-20 08:10</em>","link":"https://news.nate.com/view/20220420n05641?mid=e0608&isq=9009","retrieved":1650414362885,"image":"https://thumbnews.nateimg.co.kr/news90///news.nateimg.co.kr/orgImg/sc/2022/04/20/2022042101001587800103211.jpg"},{"title":"방탄소년단·콜드플레이 협업곡 'My Universe', 美 빌보드 장기 흥행","contents":"마이데일리\t\t\t\t\t\t\t<em>04-20 08:08</em>","link":"https://news.nate.com/view/20220420n05596?mid=e0608&isq=9009","retrieved":1650414362892,"image":"https://thumbnews.nateimg.co.kr/news90///news.nateimg.co.kr/orgImg/my/2022/04/20/202204200756206477_1.jpg"},{"title":"\"한국 잘 도착했습니다\" 방탄소년단 진, 왕사랑둥이 귀국 인사","contents":"스타뉴스\t\t\t\t\t\t\t<em>04-20 08:03</em>","link":"https://news.nate.com/view/20220420n05485?mid=e0608&isq=9009","retrieved":1650414362895,"image":"https://thumbnews.nateimg.co.kr/news90///news.nateimg.co.kr/orgImg/tn/2022/04/20/2022042007450341993_3.jpg"},{"title":"\"본업도 팬 사랑도 최고♥\" 방탄소년단 지민, 다정스윗 귀국 인사로 아미 사르르 녹여 '다녀왔습니다ㅎ!'","contents":"톱스타뉴스\t\t\t\t\t\t\t<em>04-20 08:01</em>","link":"https://news.nate.com/view/20220420n05440?mid=e0608&isq=9009","retrieved":1650414362898,"image":"https://thumbnews.nateimg.co.kr/news90///news.nateimg.co.kr/orgImg/ts/2022/04/20/14686158_784544_023_org.jpg"},{"title":"방탄소년단 정국 \"저 죽어요~\" 스파링 제안에 귀여운 화답→'추성훈' 재차 러브콜…만남 이어질까 '기대+주목'","contents":"톱스타뉴스\t\t\t\t\t\t\t<em>04-20 07:59</em>","link":"https://news.nate.com/view/20220420n05387?mid=e0608&isq=9009","retrieved":1650414362900,"image":"https://thumbnews.nateimg.co.kr/news90///news.nateimg.co.kr/orgImg/ts/2022/04/20/14686157_784535_5738_org.jpg"},{"title":"방탄소년단 뷔, LPGA 슈퍼스타 다니엘 강과 골프…美LPGA 콜라보 기대","contents":"톱스타뉴스\t\t\t\t\t\t\t<em>04-20 07:57</em>","link":"https://news.nate.com/view/20220420n05344?mid=e0608&isq=9009","retrieved":1650414362901,"image":"https://thumbnews.nateimg.co.kr/news90///news.nateimg.co.kr/orgImg/ts/2022/04/20/14686156_784532_5542_org.jpg"},{"title":"'Baby Mochi's wife' 방탄소년단 지민 찐팬들 '파파모찌' 제임스 코든과 미녀 배우 인사법","contents":"톱스타뉴스\t\t\t\t\t\t\t<em>04-20 07:55</em>","link":"https://news.nate.com/view/20220420n05316?mid=e0608&isq=9009","retrieved":1650414362903,"image":"https://thumbnews.nateimg.co.kr/news90///news.nateimg.co.kr/orgImg/ts/2022/04/20/14686155_784529_544_org.jpg"},{"title":"'다녀왔습니다ㅎ!' 방탄소년단 지민, 미소 셀카 스윗 귀국 인사…아미 사르르~♥","contents":"스타뉴스\t\t\t\t\t\t\t<em>04-20 07:53</em>","link":"https://news.nate.com/view/20220420n05287?mid=e0608&isq=9009","retrieved":1650409350571,"image":"https://thumbnews.nateimg.co.kr/news90///news.nateimg.co.kr/orgImg/tn/2022/04/20/2022042007483665797_1.jpg"},{"title":"방탄소년단X콜드플레이 'My Universe', 美빌보드 '글로벌' 차트 29주 연속 상위권","contents":"스포츠투데이\t\t\t\t\t\t\t<em>04-20 07:52</em>","link":"https://news.nate.com/view/20220420n05266?mid=e0608&isq=9009","retrieved":1650409350573,"image":"https://thumbnews.nateimg.co.kr/news90///news.nateimg.co.kr/orgImg/st/2022/04/20/20_791844_62372.jpg"}]}