{"title":"네이트 연예 ─ 아이돌24h ─ 스타 ─ BTS","url":"https://news.nate.com/ent/idolHissue?hissueSq=9009&mid=e0608","favicon":"https://news.nate.com/ent/favicon.ico","elements":[{"title":"BTS 지민X하성운, 특급 컬래버 OST 'With you' 발매","contents":"스포츠동아\t\t\t\t\t\t\t<em>04-24 09:09</em>","link":"https://news.nate.com/view/20220424n02801?mid=e0608&isq=9009","retrieved":1650759968277,"image":"https://thumbnews.nateimg.co.kr/news90///news.nateimg.co.kr/orgImg/sd/2022/04/24/113044160.1.jpg"},{"title":"방탄소년단 뷔, 스포티팔로워 700만 명 돌파…4개월 연속 K팝 솔로 증가수 1위","contents":"톱스타뉴스\t\t\t\t\t\t\t<em>04-24 09:08</em>","link":"https://news.nate.com/view/20220424n02791?mid=e0608&isq=9009","retrieved":1650759968279,"image":"https://thumbnews.nateimg.co.kr/news90///news.nateimg.co.kr/orgImg/ts/2022/04/24/14686997_785984_711_org.jpg"},{"title":"'오늘밤 11시 With You' 방탄소년단 지민 첫 OST…한국 실트1,2위•멜론 실검 장악 기대 폭발","contents":"톱스타뉴스\t\t\t\t\t\t\t<em>04-24 09:03</em>","link":"https://news.nate.com/view/20220424n02718?mid=e0608&isq=9009","retrieved":1650759968279,"image":"https://thumbnews.nateimg.co.kr/news90///news.nateimg.co.kr/orgImg/ts/2022/04/24/14686994_785972_118_org.jpg"},{"title":"BTS 지민X하성운, 오늘 '우리들의 블루스' OST 발매","contents":"스타투데이\t\t\t\t\t\t\t<em>04-24 09:01</em>","link":"https://news.nate.com/view/20220424n02677?mid=e0608&isq=9009","retrieved":1650759968284,"image":"https://thumbnews.nateimg.co.kr/news90///news.nateimg.co.kr/orgImg/tt/2022/04/24/20220424_5149279_1650758409.png"},{"title":"방탄소년단 정국 \"역시~\" 사르르 녹는 보이스X달달·나긋 '눈 맞춤' 소유욕 자극…만인이 반할 황홀한 '귀공자 자태'","contents":"톱스타뉴스\t\t\t\t\t\t\t<em>04-24 09:00</em>","link":"https://news.nate.com/view/20220424n02584?mid=e0608&isq=9009","retrieved":1650759968284,"image":"https://thumbnews.nateimg.co.kr/news90///news.nateimg.co.kr/orgImg/ts/2022/04/24/14686993_785968_5831_org.jpg"},{"title":"드디어 오늘! 방탄소년단 지민X하성운, '우리들의 블루스' OST 'With you' 발매","contents":"스타뉴스\t\t\t\t\t\t\t<em>04-24 08:43</em>","link":"https://news.nate.com/view/20220424n02433?mid=e0608&isq=9009","retrieved":1650759968286,"image":"https://thumbnews.nateimg.co.kr/news90///news.nateimg.co.kr/orgImg/tn/2022/04/24/2022042408394322002_1.jpg"},{"title":"방탄소년단 지민X하성운 부른 '블루스' OST 베일 벗는다","contents":"뉴스엔\t\t\t\t\t\t\t<em>04-24 08:38</em>","link":"https://news.nate.com/view/20220424n02368?mid=e0608&isq=9009","retrieved":1650759968287,"image":"https://thumbnews.nateimg.co.kr/news90///news.nateimg.co.kr/orgImg/nn/2022/04/24/202204240835161910_1.jpg"},{"title":"'드디어 오늘밤 11시' 방탄소년단 지민 첫OST 韓실트1·2위-멜론 실검 장악…With You♥","contents":"스타뉴스\t\t\t\t\t\t\t<em>04-24 08:30</em>","link":"https://news.nate.com/view/20220424n02283?mid=e0608&isq=9009","retrieved":1650759968289,"image":"https://thumbnews.nateimg.co.kr/news90///news.nateimg.co.kr/orgImg/tn/2022/04/24/2022042407094878099_1.jpg"},{"title":"방탄소년단 지민X하성운, 특급 컬래버…OST 오늘(24일) 발매 [공식입장]","contents":"엑스포츠뉴스\t\t\t\t\t\t\t<em>04-24 08:30</em>","link":"https://news.nate.com/view/20220424n02279?mid=e0608&isq=9009","retrieved":1650759968289,"image":"https://thumbnews.nateimg.co.kr/news90///news.nateimg.co.kr/orgImg/xs/2022/04/24/1650756537054085.jpg"},{"title":"'Butter King JIN' 방탄소년단 진, 그래미 휘어잡은 은빛 파워…시크, 도도, 매혹적 섹시","contents":"스타뉴스\t\t\t\t\t\t\t<em>04-24 08:06</em>","link":"https://news.nate.com/view/20220424n02040?mid=e0608&isq=9009","retrieved":1650759968290,"image":"https://thumbnews.nateimg.co.kr/news90///news.nateimg.co.kr/orgImg/tn/2022/04/24/2022042407430993875_1.jpg"},{"title":"\"역시 전다정씨~♥\" 방탄소년단 정국, 귀공자 자태 '황홀'","contents":"스타뉴스\t\t\t\t\t\t\t<em>04-24 07:42</em>","link":"https://news.nate.com/view/20220424n01857?mid=e0608&isq=9009","retrieved":1650754939051,"image":"https://thumbnews.nateimg.co.kr/news90///news.nateimg.co.kr/orgImg/tn/2022/04/24/2022042407385015215_1.jpg"},{"title":"방탄소년단 뷔, '세계에서 가장 유명한 K팝 아이돌' 1위…'발리우드 K팝 킹'","contents":"스타뉴스\t\t\t\t\t\t\t<em>04-24 07:38</em>","link":"https://news.nate.com/view/20220424n01830?mid=e0608&isq=9009","retrieved":1650754939055,"image":"https://thumbnews.nateimg.co.kr/news90///news.nateimg.co.kr/orgImg/tn/2022/04/24/2022042407351140214_1.jpg"},{"title":"방탄소년단 진 'Yours' 샤잠 80만 돌파…일본 TOP200 차트 15일 연속 1위 '무한질주'","contents":"스타뉴스\t\t\t\t\t\t\t<em>04-24 07:35</em>","link":"https://news.nate.com/view/20220424n01820?mid=e0608&isq=9009","retrieved":1650754939056,"image":"https://thumbnews.nateimg.co.kr/news90///news.nateimg.co.kr/orgImg/tn/2022/04/24/2022042407263244850_1.jpg"},{"title":"방탄소년단 뷔, 스포티파이 팔로워 700만 돌파…4개월 연속 K팝 솔로 최다 팔로워 증가","contents":"스타뉴스\t\t\t\t\t\t\t<em>04-24 07:22</em>","link":"https://news.nate.com/view/20220424n01745?mid=e0608&isq=9009","retrieved":1650754939059,"image":"https://thumbnews.nateimg.co.kr/news90///news.nateimg.co.kr/orgImg/tn/2022/04/24/2022042407174486811_1.jpg"},{"title":"방탄소년단 정국, 韓솔로 가수 최단 스포티파이 170만 팔로워…68일 만에 新기록 '글로벌 보컬 강자'","contents":"스타뉴스\t\t\t\t\t\t\t<em>04-24 07:16</em>","link":"https://news.nate.com/view/20220424n01716?mid=e0608&isq=9009","retrieved":1650754939062,"image":"https://thumbnews.nateimg.co.kr/news90///news.nateimg.co.kr/orgImg/tn/2022/04/24/2022042407105883491_1.jpg"}]}