{"title":"네이트 연예 ─ 아이돌24h ─ 스타 ─ BTS","url":"https://news.nate.com/ent/idolHissue?hissueSq=9009&mid=e0608","favicon":"https://news.nate.com/ent/favicon.ico","elements":[{"title":"'공항패션도 핫' 방탄소년단 뷔, 루이 비통 490만원 코트+구찌 100만원 로퍼 품절…뷔다스 효과","contents":"스타뉴스\t\t\t\t\t\t\t<em>11-18 07:12</em>","link":"https://news.nate.com/view/20211118n03569?mid=e0608&isq=9009","retrieved":1637187414170,"image":"https://thumbnews.nateimg.co.kr/news90///news.nateimg.co.kr/orgImg/tn/2021/11/18/2021111807064145247_1.jpg"},{"title":"방탄소년단X콜드플레이, '월클'의 무대 온다","contents":"스포츠경향\t\t\t\t\t\t\t<em>11-18 07:11</em>","link":"https://news.nate.com/view/20211118n03558?mid=e0608&isq=9009","retrieved":1637187414173,"image":"https://thumbnews.nateimg.co.kr/news90///news.nateimg.co.kr/orgImg/kz/2021/11/18/l_2021111802001053400213761.jpg"},{"title":"'AMAs' 방탄소년단, 콜드플레이 'My Universe' 합동 무대[공식]","contents":"스타뉴스\t\t\t\t\t\t\t<em>11-18 07:10</em>","link":"https://news.nate.com/view/20211118n03544?mid=e0608&isq=9009","retrieved":1637187414174,"image":"https://thumbnews.nateimg.co.kr/news90///news.nateimg.co.kr/orgImg/tn/2021/11/18/2021111807043561533_1.jpg"},{"title":"방탄소년단, 美 '아메리칸 뮤직 어워드'서 콜드플레이와 합동 무대 펼친다","contents":"OSEN\t\t\t\t\t\t\t<em>11-18 07:10</em>","link":"https://news.nate.com/view/20211118n03540?mid=e0608&isq=9009","retrieved":1637187414175,"image":"https://thumbnews.nateimg.co.kr/news90///news.nateimg.co.kr/orgImg/pt/2021/11/18/202111180705773412_61957d70abcc5.jpg"},{"title":"방탄소년단, 美 '아메리칸 뮤직 어워드'서 콜드플레이와 합동 무대 펼친다","contents":"스포츠투데이\t\t\t\t\t\t\t<em>11-18 07:06</em>","link":"https://news.nate.com/view/20211118n03495?mid=e0608&isq=9009","retrieved":1637187414176,"image":"https://thumbnews.nateimg.co.kr/news90///news.nateimg.co.kr/orgImg/st/2021/11/18/18_758918_32524.jpg"},{"title":"방탄소년단, 美 '2021 AMA'서 콜드플레이와 합동 무대","contents":"MK스포츠\t\t\t\t\t\t\t<em>11-18 07:06</em>","link":"https://news.nate.com/view/20211118n03493?mid=e0608&isq=9009","retrieved":1637187414178,"image":"https://thumbnews.nateimg.co.kr/news90///news.nateimg.co.kr/orgImg/aa/2021/11/18/20211118_1637186679.jpg"},{"title":"방탄소년단, 美 '2021 AMA' 콜드플레이와 합동 무대 [공식]","contents":"마이데일리\t\t\t\t\t\t\t<em>11-18 07:06</em>","link":"https://news.nate.com/view/20211118n03491?mid=e0608&isq=9009","retrieved":1637187414178,"image":"https://thumbnews.nateimg.co.kr/news90///news.nateimg.co.kr/orgImg/my/2021/11/18/202111180705393775_1.jpg"},{"title":"방탄소년단, 美 '2021 AMA'서 콜드플레이와 합동 무대(공식)","contents":"뉴스엔\t\t\t\t\t\t\t<em>11-18 07:05</em>","link":"https://news.nate.com/view/20211118n03466?mid=e0608&isq=9009","retrieved":1637187414179,"image":"https://thumbnews.nateimg.co.kr/news90///news.nateimg.co.kr/orgImg/nn/2021/11/18/202111180702032410_1.jpg"},{"title":"BTS 정국, 여심을 저격하는 강아지 조련사","contents":"엑스포츠뉴스\t\t\t\t\t\t\t<em>11-18 07:03</em>","link":"https://news.nate.com/view/20211118n03432?mid=e0608&isq=9009","retrieved":1637187414180,"image":"https://thumbnews.nateimg.co.kr/news90///news.nateimg.co.kr/orgImg/xs/2021/11/18/1637186519924435.jpg"},{"title":"방탄소년단, AMA 찍고 그래미까지…새 역사 향해[TF초점]","contents":"더팩트\t\t\t\t\t\t\t<em>11-18 07:03</em>","link":"https://news.nate.com/view/20211118n03423?mid=e0608&isq=9009","retrieved":1637187414182,"image":"https://thumbnews.nateimg.co.kr/news90///news.nateimg.co.kr/orgImg/ss/2021/11/18/202192611637133021.jpg"},{"title":"'빌보드 킹' 납시오~방탄소년단 진 'Yours' 빌보드 신흥 아티스트 톱4 데뷔…경이로운 김석진","contents":"스타뉴스\t\t\t\t\t\t\t<em>11-18 06:56</em>","link":"https://news.nate.com/view/20211118n03255?mid=e0608&isq=9009","retrieved":1637187414185,"image":"https://thumbnews.nateimg.co.kr/news90///news.nateimg.co.kr/orgImg/tn/2021/11/18/2021111806470246972_1.jpg"},{"title":"인도도 라따따따~♡ 방탄소년단 진 'Yours', 韓 솔로 최초·유일 印 IMI 진입","contents":"스타뉴스\t\t\t\t\t\t\t<em>11-18 06:46</em>","link":"https://news.nate.com/view/20211118n03148?mid=e0608&isq=9009","retrieved":1637187414187,"image":"https://thumbnews.nateimg.co.kr/news90///news.nateimg.co.kr/orgImg/tn/2021/11/18/2021111806381475066_1.jpg"},{"title":"'King of K-pop' 방탄소년단 뷔, 英 누비아 어워즈 '올해의 K팝 아이돌'","contents":"스타뉴스\t\t\t\t\t\t\t<em>11-18 06:38</em>","link":"https://news.nate.com/view/20211118n03069?mid=e0608&isq=9009","retrieved":1637187414188,"image":"https://thumbnews.nateimg.co.kr/news90///news.nateimg.co.kr/orgImg/tn/2021/11/18/2021111806333524280_1.jpg"},{"title":"방탄소년단(BTS), AMAs서 'butter'-'My Universe' 무대 펼친다","contents":"톱스타뉴스\t\t\t\t\t\t\t<em>11-18 01:32</em>","link":"https://news.nate.com/view/20211118n00714?mid=e0608&isq=9009","retrieved":1637169637229,"image":"https://thumbnews.nateimg.co.kr/news90///news.nateimg.co.kr/orgImg/ts/2021/11/18/14650089_725465_2946_org.jpg"},{"title":"'나는솔로' 4기 솔로남 대공개…\"BTS 제이홉 닮았다\"","contents":"스포츠한국\t\t\t\t\t\t\t<em>11-18 00:33</em>","link":"https://news.nate.com/view/20211118n00416?mid=e0608&isq=9009","retrieved":1637166153522,"image":"https://thumbnews.nateimg.co.kr/news90///news.nateimg.co.kr/orgImg/sh/2021/11/18/dyhero21320211118002805_O_01_C_1.jpg"}]}